reinspy/__init__.py
reinspy/_version.py
reinspy-0.0.0.dist-info/LICENSE
reinspy-0.0.0.dist-info/METADATA
reinspy-0.0.0.dist-info/WHEEL
reinspy-0.0.0.dist-info/top_level.txt
reinspy-0.0.0.dist-info/RECORD
